wadl/__init__.py
wadl/mission.py
wadl/survey.py
wadl/lib/__init__.py
wadl/lib/fence.py
wadl/lib/maze.py
wadl/lib/parameters.py
wadl/lib/route.py
wadl/solver/SATproblem.py
wadl/solver/__init__.py
wadl/solver/metaGraph.py
wadl/solver/pathTree.py
wadl/solver/pathTreeMilp.py
wadl/solver/solver.py
wadl_planner-1.1.0.dist-info/LICENSE.md
wadl_planner-1.1.0.dist-info/METADATA
wadl_planner-1.1.0.dist-info/WHEEL
wadl_planner-1.1.0.dist-info/top_level.txt
wadl_planner-1.1.0.dist-info/RECORD
