Metadata-Version: 2.1
Name: wadl-planner
Version: 1.1.0
Summary: route planner for UAV surveys
Home-page: https://github.com/k2shah/wadl
Author: Kunal Shah
Author-email: k2shah@stanford.edu
License: GNU General Public License v3 (GPL v3)
Keywords: wadl
Classifier: Development Status :: 5 - Production/Stable
Classifier: Intended Audience :: Developers
Classifier: Natural Language :: English
Classifier: Programming Language :: Python :: 3.8
Requires-Python: >=3.8
License-File: LICENSE.md
Requires-Dist: numpy
Requires-Dist: matplotlib
Requires-Dist: scipy
Requires-Dist: tqdm
Requires-Dist: shapely
Requires-Dist: networkx
Requires-Dist: utm
Requires-Dist: fastkml
Requires-Dist: lxml
Requires-Dist: z3-solver
Requires-Dist: cvxpy
Requires-Dist: cvxopt
